NLPbrl/Data_.py
NLPbrl/NLP_.py
NLPbrl/__init__.py
NLPbrl-1.0.1.dist-info/LICENSE.md
NLPbrl-1.0.1.dist-info/METADATA
NLPbrl-1.0.1.dist-info/WHEEL
NLPbrl-1.0.1.dist-info/top_level.txt
NLPbrl-1.0.1.dist-info/RECORD
