Metadata-Version: 2.1
Name: NLPbrl
Version: 1.0.1
Summary: NLP algorithm integration package
Home-page: https://github.com/KingOfOrikid/proj_NLPbrl_DATA534
Author: Yuxin Chen & Siyue Gao
Author-email: yuxin.yuki.chen@gmail.com
License: MIT
Platform: UNKNOWN
License-File: LICENSE.md
